{
  "kind": "collectionType",
  "collectionName": "routines",
  "info": {
    "singularName": "routine",
    "pluralName": "routines",
    "displayName": "routine",
    "description": ""
  },
  "options": {
    "draftAndPublish": false
  },
  "pluginOptions": {},
  "attributes": {
    "name": {
      "type": "string"
    },
    "user": {
      "type": "relation",
      "relation": "oneToOne",
      "target": "plugin::users-permissions.user"
    },
    "description": {
      "type": "string"
    }
  }
}
